RAMSTK-1.0.1.data/data/share/RAMSTK/RAMSTK.conf
RAMSTK-1.0.1.data/data/share/RAMSTK/Site.conf
RAMSTK-1.0.1.data/data/share/RAMSTK/ramstk_common.rtk
RAMSTK-1.0.1.data/data/share/RAMSTK/icons/16x16/add.png
RAMSTK-1.0.1.data/data/share/RAMSTK/icons/16x16/assembly.png
RAMSTK-1.0.1.data/data/share/RAMSTK/icons/16x16/calculate-all.png
RAMSTK-1.0.1.data/data/share/RAMSTK/icons/16x16/calculate.png
RAMSTK-1.0.1.data/data/share/RAMSTK/icons/16x16/calendar.png
RAMSTK-1.0.1.data/data/share/RAMSTK/icons/16x16/copy.png
RAMSTK-1.0.1.data/data/share/RAMSTK/icons/16x16/cut.png
RAMSTK-1.0.1.data/data/share/RAMSTK/icons/16x16/db-export.png
RAMSTK-1.0.1.data/data/share/RAMSTK/icons/16x16/db-import.png
RAMSTK-1.0.1.data/data/share/RAMSTK/icons/16x16/exit.png
RAMSTK-1.0.1.data/data/share/RAMSTK/icons/16x16/filter.png
RAMSTK-1.0.1.data/data/share/RAMSTK/icons/16x16/help.png
RAMSTK-1.0.1.data/data/share/RAMSTK/icons/16x16/import.png
RAMSTK-1.0.1.data/data/share/RAMSTK/icons/16x16/new.png
RAMSTK-1.0.1.data/data/share/RAMSTK/icons/16x16/open.png
RAMSTK-1.0.1.data/data/share/RAMSTK/icons/16x16/options.png
RAMSTK-1.0.1.data/data/share/RAMSTK/icons/16x16/part.png
RAMSTK-1.0.1.data/data/share/RAMSTK/icons/16x16/paste.png
RAMSTK-1.0.1.data/data/share/RAMSTK/icons/16x16/preferences-desktop.png
RAMSTK-1.0.1.data/data/share/RAMSTK/icons/16x16/preferences-system.png
RAMSTK-1.0.1.data/data/share/RAMSTK/icons/16x16/preferences.png
RAMSTK-1.0.1.data/data/share/RAMSTK/icons/16x16/redo.png
RAMSTK-1.0.1.data/data/share/RAMSTK/icons/16x16/remove.png
RAMSTK-1.0.1.data/data/share/RAMSTK/icons/16x16/save.png
RAMSTK-1.0.1.data/data/share/RAMSTK/icons/16x16/undo.png
RAMSTK-1.0.1.data/data/share/RAMSTK/icons/32x32/about.png
RAMSTK-1.0.1.data/data/share/RAMSTK/icons/32x32/accelerated.png
RAMSTK-1.0.1.data/data/share/RAMSTK/icons/32x32/action.png
RAMSTK-1.0.1.data/data/share/RAMSTK/icons/32x32/add.png
RAMSTK-1.0.1.data/data/share/RAMSTK/icons/32x32/assembly.png
RAMSTK-1.0.1.dist-info/METADATA
RAMSTK-1.0.1.dist-info/RECORD
RAMSTK-1.0.1.dist-info/WHEEL
RAMSTK-1.0.1.dist-info/entry_points.txt
RAMSTK-1.0.1.dist-info/top_level.txt
RAMSTK-1.0.1.dist-info/zip-safe
