Metadata-Version: 2.1
Name: RAMSTK
Version: 1.0.1
Summary: The RAMS ToolKit (RAMSTK) is a suite of tools
Home-page: https://github.com/weibullguy/ramstk
Author: Doyle 'weibullguy' Rowland
Author-email: doyle.rowland@reliaqual.com
License: BSD-3
Keywords: reliability availability maintainability safety RAMS
Platform: UNKNOWN
Classifier: Development Status :: 4 - Beta
Classifier: Environment :: Win32 (MS Windows)
Classifier: Environment :: X11 Applications :: GTK
Classifier: Intended Audience :: Other Audience
Classifier: License :: OSI Approved :: BSD License
Classifier: Programming Language :: Python :: 2.7
Classifier: Topic :: Scientific/Engineering :: Electronic Design Automation (EDA)
Requires-Python: >=2.7, <4
Requires-Dist: defusedxml
Requires-Dist: lifelines
Requires-Dist: matplotlib (==1.4.3)
Requires-Dist: numpy
Requires-Dist: pandas
Requires-Dist: PyPubSub (==3.3.0)
Requires-Dist: scipy
Requires-Dist: sortedcontainers (==1.5.9)
Requires-Dist: SQLAlchemy
Requires-Dist: SQLAlchemy-Utils
Requires-Dist: statsmodels
Requires-Dist: treelib
Requires-Dist: xlrd
Requires-Dist: xlwt
